{
  "openIssues": 100,
  "issuesClosedLastHour": 0,
  "issuesClosedLastDay": 100,
  "openPRs": 0,
  "prDetails": [],
  "diffMinutes": 10,
  "diffMinutesMain": 10,
  "commitsLastHour": 5,
  "commitsLastDay": 88,
  "lastFiveCommitMessages": [
    {
      "time": "09:28",
      "message": "Maintain ONTOLOGY_SERVICE"
    },
    {
      "time": "09:13",
      "message": "Maintain MODEL_FACTORY"
    },
    {
      "time": "09:02",
      "message": "Maintain ONTOLOGY_SERVICE"
    },
    {
      "time": "08:52",
      "message": "Maintain TELEMETRY_SUMMARY"
    },
    {
      "time": "08:41",
      "message": "Maintain NOTIFICATIONS"
    }
  ],
  "branches": {
    "count": 1,
    "details": [
      {
        "branch": "agentic-lib-issue-902",
        "minutesSinceLastCommit": 175
      }
    ]
  },
  "averagePRAge": 0,
  "testStatus": "PASS",
  "testsLastPassedMinutes": 15,
  "generatedAt": "2025-04-09T09:38:40.161Z"
}