{
  "openIssues": 34,
  "issuesClosedLastHour": 0,
  "issuesClosedLastDay": 100,
  "openPRs": 0,
  "prDetails": [],
  "diffMinutes": 3,
  "diffMinutesMain": 3,
  "commitsLastHour": 6,
  "commitsLastDay": 100,
  "lastFiveCommitMessages": [
    {
      "time": "05:33",
      "message": "Maintain SCHEMA_MANAGER"
    },
    {
      "time": "05:22",
      "message": "Maintain SCHEMA_MANAGER"
    },
    {
      "time": "05:11",
      "message": "Maintain SCHEMA_MANAGER"
    },
    {
      "time": "05:00",
      "message": "Maintain SCHEMA_MANAGER"
    },
    {
      "time": "04:53",
      "message": "Maintain SCHEMA_MANAGER"
    }
  ],
  "branches": {
    "count": 1,
    "details": [
      {
        "branch": "agentic-lib-issue-1050",
        "minutesSinceLastCommit": 24
      }
    ]
  },
  "averagePRAge": 0,
  "testStatus": "PASS",
  "testsLastPassedMinutes": 15,
  "generatedAt": "2025-04-10T05:37:01.507Z"
}